milocode/__init__.py
milocode-0.1.111a2.dist-info/LICENSE
milocode-0.1.111a2.dist-info/METADATA
milocode-0.1.111a2.dist-info/WHEEL
milocode-0.1.111a2.dist-info/RECORD
