Metadata-Version: 2.1
Name: milocode
Version: 0.1.111a2
Summary: The all-in-one voice SDK
Home-page: https://github.com/vocodedev/vocode-python
License: MIT
Author: Ajay Raj
Author-email: ajay@vocode.dev
Requires-Python: >=3.8.1,<3.12
Classifier: License :: OSI Approved :: MIT License
Classifier: Programming Language :: Python :: 3
Classifier: Programming Language :: Python :: 3.9
Classifier: Programming Language :: Python :: 3.10
Classifier: Programming Language :: Python :: 3.11
Provides-Extra: actions
Provides-Extra: agents
Provides-Extra: all
Provides-Extra: synthesizers
Provides-Extra: telephony
Provides-Extra: transcribers
Requires-Dist: aiohttp (>=3.8.4,<4.0.0)
Requires-Dist: anthropic (>=0.2.9,<0.3.0)
Requires-Dist: azure-cognitiveservices-speech (>=1.27.0,<2.0.0)
Requires-Dist: elevenlabs (>=0.2.6,<0.3.0) ; extra == "synthesizers" or extra == "all"
Requires-Dist: fastapi (>=0.95.1,<0.96.0)
Requires-Dist: google-cloud-aiplatform (>=1.26.0,<2.0.0) ; extra == "agents" or extra == "all"
Requires-Dist: google-cloud-speech (>=2.19.0,<3.0.0) ; extra == "transcribers" or extra == "all"
Requires-Dist: google-cloud-texttospeech (>=2.14.1,<3.0.0) ; extra == "synthesizers" or extra == "all"
Requires-Dist: gtts (>=2.3.1,<3.0.0) ; extra == "synthesizers" or extra == "all"
Requires-Dist: janus (>=1.0.0,<2.0.0)
Requires-Dist: jinja2 (>=3.1.2,<4.0.0)
Requires-Dist: langchain (>=0.0.198,<0.0.199)
Requires-Dist: nltk (>=3.8.1,<4.0.0)
Requires-Dist: nylas (>=5.14.0,<6.0.0) ; extra == "actions" or extra == "all"
Requires-Dist: openai (>=0.27.8,<0.28.0)
Requires-Dist: opentelemetry-sdk (>=1.17.0,<2.0.0)
Requires-Dist: pydub (>=0.25.1,<0.26.0)
Requires-Dist: python-multipart (>=0.0.6,<0.0.7)
Requires-Dist: redis (>=4.5.4,<5.0.0) ; extra == "telephony" or extra == "all"
Requires-Dist: requests (>=2.28.2,<3.0.0)
Requires-Dist: scipy (>=1.10.1,<2.0.0)
Requires-Dist: six (>=1.16.0,<2.0.0)
Requires-Dist: sounddevice (>=0.4.6,<0.5.0)
Requires-Dist: speechrecognition (>=3.10.0,<4.0.0)
Requires-Dist: twilio (>=8.1.0,<9.0.0) ; extra == "telephony" or extra == "all"
Requires-Dist: uvicorn (>=0.21.1,<0.22.0)
Requires-Dist: vonage (>=3.5.1,<4.0.0) ; extra == "telephony" or extra == "all"
Requires-Dist: websockets (>=11.0.2,<12.0.0)
